compresso.cpython-37m-darwin.so
compresso_cli/__init__.py
compresso_cli/cli.py
compresso-3.3.3.dist-info/RECORD
compresso-3.3.3.dist-info/LICENSE
compresso-3.3.3.dist-info/AUTHORS
compresso-3.3.3.dist-info/WHEEL
compresso-3.3.3.dist-info/COPYING.LESSER
compresso-3.3.3.dist-info/entry_points.txt
compresso-3.3.3.dist-info/pbr.json
compresso-3.3.3.dist-info/top_level.txt
compresso-3.3.3.dist-info/METADATA
